magic_mouse_gestures.py
magic_mouse_gestures-0.1.0.dist-info/licenses/LICENSE
magic_mouse_gestures-0.1.0.dist-info/METADATA
magic_mouse_gestures-0.1.0.dist-info/WHEEL
magic_mouse_gestures-0.1.0.dist-info/entry_points.txt
magic_mouse_gestures-0.1.0.dist-info/top_level.txt
magic_mouse_gestures-0.1.0.dist-info/RECORD
