Metadata-Version: 2.4
Name: magic-mouse-gestures
Version: 0.1.0
Summary: macOS-style swipe gestures for Apple Magic Mouse 2 on Linux/Wayland
Author-email: Breno Perucchi <breno@example.com>
License: MIT
Project-URL: Homepage, https://github.com/brenoperucchi/magic-mouse-gestures
Project-URL: Repository, https://github.com/brenoperucchi/magic-mouse-gestures
Project-URL: Issues, https://github.com/brenoperucchi/magic-mouse-gestures/issues
Keywords: magic-mouse,gestures,linux,wayland,macos
Classifier: Development Status :: 3 - Alpha
Classifier: Intended Audience :: End Users/Desktop
Classifier: License :: OSI Approved :: MIT License
Classifier: Operating System :: POSIX :: Linux
Classifier: Programming Language :: Python :: 3
Classifier: Programming Language :: Python :: 3.8
Classifier: Programming Language :: Python :: 3.9
Classifier: Programming Language :: Python :: 3.10
Classifier: Programming Language :: Python :: 3.11
Classifier: Programming Language :: Python :: 3.12
Requires-Python: >=3.8
License-File: LICENSE
Dynamic: license-file
